just_facebook_mcp/__init__.py
just_facebook_mcp/config.py
just_facebook_mcp/facebook_api.py
just_facebook_mcp/manager.py
just_facebook_mcp/server.py
just_facebook_mcp-0.1.0.dist-info/METADATA
just_facebook_mcp-0.1.0.dist-info/WHEEL
just_facebook_mcp-0.1.0.dist-info/entry_points.txt
just_facebook_mcp-0.1.0.dist-info/licenses/LICENSE
just_facebook_mcp-0.1.0.dist-info/RECORD
