Metadata-Version: 2.4
Name: just_facebook_mcp
Version: 0.1.0
Summary: MCP server for automating and managing interactions on a Facebook Page using the Facebook Graph API
Project-URL: Homepage, https://github.com/Livia-Zaharia/just_facebook_mcp
Project-URL: Repository, https://github.com/Livia-Zaharia/just_facebook_mcp
Project-URL: Issues, https://github.com/Livia-Zaharia/just_facebook_mcp/issues
Author: HagaiHen
Author-email: Livia Zaharia <liviazaharia2020@gmail.com>
License-Expression: MIT
License-File: LICENSE
Keywords: api,automation,facebook,mcp,social-media
Classifier: Development Status :: 4 - Beta
Classifier: Intended Audience :: Developers
Classifier: License :: OSI Approved :: MIT License
Classifier: Programming Language :: Python :: 3
Classifier: Programming Language :: Python :: 3.10
Classifier: Programming Language :: Python :: 3.11
Classifier: Programming Language :: Python :: 3.12
Classifier: Topic :: Communications :: Chat
Classifier: Topic :: Internet :: WWW/HTTP :: Dynamic Content
Classifier: Topic :: Software Development :: Libraries :: Python Modules
Requires-Python: >=3.10
Requires-Dist: mcp
Requires-Dist: python-dotenv
Requires-Dist: requests
Provides-Extra: build
Requires-Dist: build; extra == 'build'
Requires-Dist: hatch; extra == 'build'
Requires-Dist: twine; extra == 'build'
Provides-Extra: dev
Requires-Dist: black; extra == 'dev'
Requires-Dist: flake8; extra == 'dev'
Requires-Dist: mypy; extra == 'dev'
Requires-Dist: pytest; extra == 'dev'
Requires-Dist: pytest-cov; extra == 'dev'
